country_acronyms/__init__.py
country_acronyms/acronyms.py
country_acronyms-0.0.7.dist-info/LICENCE
country_acronyms-0.0.7.dist-info/METADATA
country_acronyms-0.0.7.dist-info/WHEEL
country_acronyms-0.0.7.dist-info/top_level.txt
country_acronyms-0.0.7.dist-info/RECORD
