Metadata-Version: 2.1
Name: country-acronyms
Version: 0.0.7
Summary: All possible translations, acronyms for a specific country name / country iso
Home-page: https://github.com/Ad4mk0/country_acronyms
Author: Adam Mikulasek
Author-email: mikulasek.adam@gmail.com
Project-URL: Bug Tracker, https://github.com/Ad4mk0/country_acronyms/issues
Classifier: Programming Language :: Python :: 3
Classifier: License :: OSI Approved :: MIT License
Classifier: Operating System :: OS Independent
Requires-Python: >=3.6
License-File: LICENCE
